deshima_rawdata/__init__.py
deshima_rawdata/cli.py
deshima_rawdata/data.csv
deshima_rawdata/py.typed
deshima_rawdata-2024.4.2.dist-info/LICENSE
deshima_rawdata-2024.4.2.dist-info/METADATA
deshima_rawdata-2024.4.2.dist-info/WHEEL
deshima_rawdata-2024.4.2.dist-info/entry_points.txt
deshima_rawdata-2024.4.2.dist-info/RECORD
