Metadata-Version: 2.1
Name: deshima-rawdata
Version: 2024.4.2
Summary: DESHIMA raw data and downloader package
License: MIT
Author: Akio Taniguchi
Author-email: taniguchi@a.phys.nagoya-u.ac.jp
Requires-Python: >=3.9,<3.13
Classifier: License :: OSI Approved :: MIT License
Classifier: Programming Language :: Python :: 3
Classifier: Programming Language :: Python :: 3.9
Classifier: Programming Language :: Python :: 3.10
Classifier: Programming Language :: Python :: 3.11
Classifier: Programming Language :: Python :: 3.12
Requires-Dist: fire (>=0.5,<0.6)
Requires-Dist: packaging (>=23.0,<24.0)
Requires-Dist: pandas[output-formatting] (>=1.5,<3.0)
Requires-Dist: requests (>=2.30,<3.0)
Requires-Dist: tqdm (>=4.65,<5.0)
